elia_opendata/__init__.py
elia_opendata/client.py
elia_opendata/data_processor.py
elia_opendata/dataset_catalog.py
elia_opendata/error.py
elia_opendata-1.0.2.dist-info/METADATA
elia_opendata-1.0.2.dist-info/WHEEL
elia_opendata-1.0.2.dist-info/licenses/LICENSE
elia_opendata-1.0.2.dist-info/RECORD
