Metadata-Version: 2.4
Name: elia_opendata
Version: 1.0.2
Summary: Python Client for Elia Open Data
Author: WattsToAnalyze
License: MIT
License-File: LICENSE
Requires-Python: >=3.7
Requires-Dist: numpy>=1.24.0
Requires-Dist: pandas>=2.0.0
Requires-Dist: polars>=0.20.0
Requires-Dist: pyarrow>=14.0.1
Requires-Dist: requests>=2.25.0
Provides-Extra: docs
Requires-Dist: ipykernel>=6.0.0; extra == 'docs'
Requires-Dist: jupyter>=1.0.0; extra == 'docs'
Requires-Dist: matplotlib>=3.5.0; extra == 'docs'
Requires-Dist: mkdocs-autorefs>=0.5.0; extra == 'docs'
Requires-Dist: mkdocs-material>=9.0.0; extra == 'docs'
Requires-Dist: mkdocs>=1.5.0; extra == 'docs'
Requires-Dist: mkdocstrings-python>=1.7.0; extra == 'docs'
Requires-Dist: mkdocstrings>=0.24.0; extra == 'docs'
Requires-Dist: nbformat>=5.0.0; extra == 'docs'
Provides-Extra: test
Requires-Dist: flake8>=6.0.0; extra == 'test'
Requires-Dist: mypy>=1.0.0; extra == 'test'
Requires-Dist: pandas-stubs>=2.0.0; extra == 'test'
Requires-Dist: pytest-cov>=4.0.0; extra == 'test'
Requires-Dist: pytest>=7.0.0; extra == 'test'
Requires-Dist: responses>=0.23.0; extra == 'test'
Requires-Dist: types-pytz>=2023.0.0; extra == 'test'
Requires-Dist: types-requests>=2.25.0; extra == 'test'
